exso_sdk/__init__.py
exso_sdk/config.py
exso_sdk/data.py
exso_sdk/explain.py
exso_sdk/features.py
exso_sdk/metrics.py
exso_sdk/model.py
exso_sdk/preprocessing.py
exso_sdk/utils.py
exso_sdk/model_data/__init__.py
exso_sdk/model_data/exoplanet_model.pth
exso_sdk/model_data/v2/__init__.py
exso_sdk/model_data/v2/exo_label_encoder.pkl
exso_sdk/model_data/v2/exo_stacking_pipeline.pkl
exso_sdk-2.0.1.dist-info/METADATA
exso_sdk-2.0.1.dist-info/WHEEL
exso_sdk-2.0.1.dist-info/top_level.txt
exso_sdk-2.0.1.dist-info/RECORD
