Metadata-Version: 2.4
Name: exso-sdk
Version: 2.0.1
Summary: Exoplanet candidate classification SDK V2 with stacking ensemble model (LightGBM + XGBoost + CatBoost)
Author-email: Darwin Danish <lumina.ai.devs@gmail.com>
License-Expression: MIT
Project-URL: Homepage, https://github.com/yourname/exso-sdk
Project-URL: Repository, https://github.com/yourname/exso-sdk
Project-URL: Documentation, https://exso-sdk.readthedocs.io
Project-URL: Bug Tracker, https://github.com/yourname/exso-sdk/issues
Classifier: Development Status :: 5 - Production/Stable
Classifier: Intended Audience :: Science/Research
Classifier: Programming Language :: Python :: 3
Classifier: Programming Language :: Python :: 3.8
Classifier: Programming Language :: Python :: 3.9
Classifier: Programming Language :: Python :: 3.10
Classifier: Programming Language :: Python :: 3.11
Classifier: Programming Language :: Python :: 3.12
Classifier: Topic :: Scientific/Engineering :: Artificial Intelligence
Classifier: Topic :: Scientific/Engineering :: Astronomy
Classifier: Operating System :: OS Independent
Requires-Python: >=3.8
Requires-Dist: numpy<1.25,>=1.23
Requires-Dist: pandas==2.0.3
Requires-Dist: scikit-learn>=1.0.0
Requires-Dist: lightgbm>=3.3.0
Requires-Dist: xgboost>=1.6.0
Requires-Dist: catboost>=1.0.0
Requires-Dist: joblib>=1.1.0
Requires-Dist: flask==2.3.3
Requires-Dist: flask-cors==4.0.0
Requires-Dist: openpyxl==3.1.2
Requires-Dist: werkzeug==2.3.7
Provides-Extra: dev
Requires-Dist: pytest>=6.0; extra == "dev"
Requires-Dist: pytest-cov>=2.0; extra == "dev"
Requires-Dist: black>=21.0; extra == "dev"
Requires-Dist: flake8>=3.8; extra == "dev"
Requires-Dist: mypy>=0.800; extra == "dev"
Provides-Extra: docs
Requires-Dist: sphinx>=4.0; extra == "docs"
Requires-Dist: sphinx-rtd-theme>=0.5; extra == "docs"
